vortex_tools/__init__.py
vortex_tools/markers.py
vortex_tools/profiler.py
vortex_tools/scan.py
vortex_tools/ui/__init__.py
vortex_tools/ui/display.py
vortex_tools/ui/backend/__init__.py
vortex_tools/ui/backend/__main__.py
vortex_tools/ui/backend/base.py
vortex_tools/ui/backend/mpl.py
vortex_tools/ui/backend/qt.py
vortex_oct_tools-0.3.0.dist-info/LICENSE
vortex_oct_tools-0.3.0.dist-info/METADATA
vortex_oct_tools-0.3.0.dist-info/WHEEL
vortex_oct_tools-0.3.0.dist-info/top_level.txt
vortex_oct_tools-0.3.0.dist-info/RECORD
