Metadata-Version: 2.2
Name: vortex_oct_tools
Version: 0.3.0
Summary: Python Tools for Vortex
Author-email: Mark Draelos <mdraelos@umich.edu>
License: BSD 3-Clause License
Project-URL: Homepage, https://www.vortex-oct.dev/
Classifier: Development Status :: 4 - Beta
Classifier: Intended Audience :: Developers
Classifier: License :: OSI Approved :: BSD License
Classifier: Operating System :: OS Independent
Classifier: Programming Language :: Python :: 3
Classifier: Topic :: Scientific/Engineering
Requires-Python: >=3.6
License-File: LICENSE
Requires-Dist: numpy
Requires-Dist: pandas
Requires-Dist: matplotlib
Requires-Dist: qtpy
